nua_cli/__init__.py
nua_cli/client.py
nua_cli/commands/__init__.py
nua_cli/commands/apps.py
nua_cli/commands/backup.py
nua_cli/commands/build.py
nua_cli/commands/common.py
nua_cli/commands/config.py
nua_cli/commands/deploy.py
nua_cli/commands/env.py
nua_cli/commands/help.py
nua_cli/commands/lifecycle.py
nua_cli/commands/logs.py
nua_cli/commands/main.py
nua_cli/commands/server.py
nua_cli/common.py
nua_cli/main.py
nua_cli/version.py
nua-0.5.43.dist-info/METADATA
nua-0.5.43.dist-info/WHEEL
nua-0.5.43.dist-info/entry_points.txt
nua-0.5.43.dist-info/RECORD
