Metadata-Version: 2.1
Name: nua
Version: 0.5.43
Summary: Command line interface for the Nua self-hosted PaaS (Platform as a Service)
Home-page: https://github.com/abilian/nua
License: Apache-2.0
Author: Stefane Fermigier
Author-email: sf@abilian.com
Requires-Python: >=3.10,<3.12
Classifier: Development Status :: 3 - Alpha
Classifier: Environment :: Console
Classifier: Intended Audience :: Developers
Classifier: Intended Audience :: System Administrators
Classifier: License :: OSI Approved :: Apache Software License
Classifier: Programming Language :: Python :: 3
Classifier: Programming Language :: Python :: 3.10
Classifier: Programming Language :: Python :: 3.11
Requires-Dist: cleez (>=0.1.9,<0.2.0)
Requires-Dist: decorator (>=5.1.1,<6.0.0)
Requires-Dist: fabric (>=3.0,<3.1)
Requires-Dist: snoop
Requires-Dist: tomli (>=2.0.1,<3.0.0)
Project-URL: Documentation, https://nua.rocks/
Project-URL: Repository, https://github.com/abilian/nua
